COPYING
LICENSE
MANIFEST.in
README.txt
ez_setup.py
setup.py
py_restclient.egg-info/PKG-INFO
py_restclient.egg-info/SOURCES.txt
py_restclient.egg-info/dependency_links.txt
py_restclient.egg-info/entry_points.txt
py_restclient.egg-info/requires.txt
py_restclient.egg-info/top_level.txt
py_restclient.egg-info/zip-safe
restclient/__init__.py
restclient/errors.py
restclient/rest.py
restclient/utils.py
restclient/bin/__init__.py
restclient/bin/rest_cli.py
restclient/transport/__init__.py
restclient/transport/_curl.py
restclient/transport/_httplib2.py
restclient/transport/base.py
tests/__init__.py
tests/_server_test.py
tests/curl_test.py
tests/resource_test.py
tests/transports_test.py
tests/utils_test.py