Metadata-Version: 1.0
Name: py-restclient
Version: 1.3.3
Summary: Python REST client
Home-page: http://py-restclient.e-engura.org
Author: Benoit Chesneau
Author-email: benoitc@e-engura.org
License: BSD
Platform: UNKNOWN
Classifier: Development Status :: 4 - Beta
Classifier: Environment :: Web Environment
Classifier: Intended Audience :: Developers
Classifier: License :: OSI Approved :: MIT License
Classifier: Operating System :: OS Independent
Classifier: Programming Language :: Python
Classifier: Topic :: Internet :: WWW/HTTP
Classifier: Topic :: Software Development :: Libraries
